intrisk/__init__.py
intrisk/intrisk.py
intrisk-0.0.2.dist-info/LICENSE
intrisk-0.0.2.dist-info/METADATA
intrisk-0.0.2.dist-info/WHEEL
intrisk-0.0.2.dist-info/top_level.txt
intrisk-0.0.2.dist-info/RECORD
