Metadata-Version: 2.1
Name: intrisk
Version: 0.0.2
Summary: Package with routines to extract data and model natural hazards and changes in risk.
Home-page: https://github.com/felwind14/intrisk
Author: Felipe Fonseca
Author-email: felipe.fonsecaa14@gmail.com
License: MIT license
Keywords: intrisk
Classifier: Development Status :: 2 - Pre-Alpha
Classifier: Intended Audience :: Developers
Classifier: License :: OSI Approved :: MIT License
Classifier: Natural Language :: English
Classifier: Programming Language :: Python :: 3
Classifier: Programming Language :: Python :: 3.7
Classifier: Programming Language :: Python :: 3.8
Classifier: Programming Language :: Python :: 3.9
Classifier: Programming Language :: Python :: 3.10
Requires-Python: >=3.7
License-File: LICENSE
